README.md
setup.py
megstudio/__init__.py
megstudio/logger.py
megstudio.egg-info/PKG-INFO
megstudio.egg-info/SOURCES.txt
megstudio.egg-info/dependency_links.txt
megstudio.egg-info/requires.txt
megstudio.egg-info/top_level.txt
megstudio/data/__init__.py
megstudio/data/dataset/__init__.py
megstudio/data/dataset/meta_dataset.py
megstudio/data/dataset/vision/__init__.py
megstudio/data/dataset/vision/cifar.py
megstudio/data/dataset/vision/folder.py
megstudio/data/dataset/vision/imagenet.py
megstudio/data/dataset/vision/meta_vision.py
megstudio/data/dataset/vision/utils.py