Metadata-Version: 2.1
Name: megstudio
Version: 0.0.4
Summary: megstudio package
Home-page: https://github.com/pypa/sampleproject
Author: Renyang
Author-email: renyang@megvii.com
License: MIT
Platform: UNKNOWN
Classifier: Programming Language :: Python :: 3
Classifier: License :: OSI Approved :: MIT License
Classifier: Operating System :: OS Independent
Requires-Python: >=3.6
